flask_mongoengine/__init__.py
flask_mongoengine/connection.py
flask_mongoengine/json.py
flask_mongoengine/operation_tracker.py
flask_mongoengine/pagination.py
flask_mongoengine/panels.py
flask_mongoengine/sessions.py
flask_mongoengine/templates/panels/mongo-panel.html
flask_mongoengine/wtf/__init__.py
flask_mongoengine/wtf/base.py
flask_mongoengine/wtf/fields.py
flask_mongoengine/wtf/models.py
flask_mongoengine/wtf/orm.py
flask_mongoengine-0.9.5.dist-info/DESCRIPTION.rst
flask_mongoengine-0.9.5.dist-info/METADATA
flask_mongoengine-0.9.5.dist-info/RECORD
flask_mongoengine-0.9.5.dist-info/WHEEL
flask_mongoengine-0.9.5.dist-info/metadata.json
flask_mongoengine-0.9.5.dist-info/top_level.txt
